fwd9m/__init__.py
tensorflow_determinism-0.4.0.dist-info/DESCRIPTION.rst
tensorflow_determinism-0.4.0.dist-info/METADATA
tensorflow_determinism-0.4.0.dist-info/RECORD
tensorflow_determinism-0.4.0.dist-info/WHEEL
tensorflow_determinism-0.4.0.dist-info/metadata.json
tensorflow_determinism-0.4.0.dist-info/top_level.txt
tfdeterminism/__init__.py
