Metadata-Version: 2.0
Name: tensorflow-determinism
Version: 0.4.0
Summary: Providing reproducibility in deep learning frameworks
Home-page: https://github.com/NVIDIA/tensorflow-determinism
Author: NVIDIA
Author-email: duncan@nvidia.com
License: Apache 2.0
Platform: UNKNOWN
